rtl/uart16550_axil.v
/******************************************************************************
AXI Lite 16550 Compatible Uart

#Included modules
The modules are listed in order they appear
+ uart1655_axil_tickgen
******************************************************************************/

/******************************************************************************
uart1655_axil_tickgen

#Description
The tickgen module generates the timing reference for the transmitter.
By looping back the external port, the internal tickgen can also be used
as receiver timing reference. The tick output is generated by
dividing the clk signal by the value of presc. Important to note is
that the tick clock has a duty cycle 1/[presc-1]. The signal is only
high for one cycle of the clk signal.

#Port List
+ presc [15:0] unsigned int -- prescaler for tick signal
+ tick         bool         -- divided clock signal
+ clk          bool         -- system clock
+ reset_n      bool         -- system reset
******************************************************************************/

module uart1655_axil_tickgen (
    input   wire    [15:0]     presc,
    output  wire               tick,
    input   wire               clk,
    input   wire               reset_n
);

reg     [15:0]     presc_r;
wire               passthrough = (presc == 16'b1);
wire               stop        = (presc == 16'b0);

always @ (posedge clk, negedge reset_n)
begin
    if( !reset_n || passthrough || stop ) begin
        presc_r <= 0;
    end
    else begin
        presc_r <= (presc_r == 0) ? presc-1 : presc_r-1;
    end
end

assign tick = passthrough ? clk : (presc_r == 0);

endmodule

/******************************************************************************
uart1655_axil_fifo
#Description
#Port List
******************************************************************************/

module uart1655_axil_fifo(
    input   wire            regmode,
    input   wire    [7:0]   idata,
    input   wire            write,
    output  wire    [7:0]   odata,
    input   wire            read,
    output  wire    [4:0]   elems,
    output  wire            empty,
    output  wire            full,
    output  reg             oeflag,
    input   wire            clear_flag,
    input   wire            clk,
    input   wire            reset_n
);
//==Local parameters
localparam WIDTH = 8;
localparam DEPTH = 16;

//==Signals and Registers
reg     [WIDTH-1:0]     mem [0:DEPTH-1];
reg     [4:0]           elems_r;
reg     [3:0]           wptr;
reg     [3:0]           rptr;
wire                    valid_write;
wire                    valid_read;
reg                     reg_full;

//==Sequention logic
always @ (posedge clk, negedge reset_n)
begin
    if( !reset_n || regmode ) begin
        elems_r <= 5'b0;
    end
    else begin
        case( {valid_read, valid_write} )
            2'b01:
                elems_r <= elems_r + 1'b1;
            2'b10:
                elems_r <= elems_r - 1'b1;
            default:
                elems_r <= elems_r;
        endcase
    end
end

always @ (posedge clk, negedge reset_n)
begin
    if( !reset_n || regmode ) begin
        wptr <= 0;
    end
    else begin
        if( valid_write ) begin
            wptr <= wptr + 1'b1;
        end
    end
end

always @ (posedge clk)
begin
    if( valid_write ) begin
        mem[wptr] <= idata;
    end
end

always @ (posedge clk, negedge reset_n)
begin
    if( !reset_n || regmode ) begin
        rptr <= 0;
    end
    else begin
        if( valid_read ) begin
            rptr <= rptr + 1'b1;
        end
    end
end

always @ (posedge clk, negedge reset_n)
begin
    if( !reset_n ) begin
        oeflag <= 0;
    end
    else begin
        if( oeflag ) begin
            oeflag <= clear_flag ? (write & full) : 1'b1;
        end
        else begin
            oeflag <= write & full;
        end
    end
end

always @ (posedge clk, negedge reset_n)
begin
    if( !reset_n ) begin
        reg_full <= 1'b0;
    end
    else begin
        if( reg_full ) begin
            reg_full <= read ? write : 1'b1;
        end
        else begin
            reg_full <= write;
        end
    end
end

//==Static assignements
assign elems = elems_r;
assign empty = (elems_r == 0);
assign full = (elems_r == 16);
assign valid_read = (read & !empty);
assign valid_write = (write & !full);
assign odata = mem[rptr];

endmodule

test/fifotest.v
`timescale 1ns/10ps

`define assert( signal, value )\
    if( signal != value ) begin\
        $display( "[%010d] Assertion Failed! signal != value @ %m", $time );\
        $finish;\
    end\

module fifotest();
localparam MAX_SLEN = 32;

//==Signals
reg     [7:0]   scratch;
reg     [7:0]   rdata;
reg     [7:0]   wdata;
reg     [7:0]   i;
reg             regmode = 1'b0;
reg     [7:0]   idata;
reg             write;
wire    [7:0]   odata;
reg             read;
wire    [4:0]   elems;
wire            empty;
wire            full;
wire            oeflag;
reg             clear_flag = 1'b0;
reg             clk;
reg             reset_n;
reg     [MAX_SLEN*8:0]  tname;

//==Tasks
task enqueue(
    input [7:0]   data
);
begin
    @(posedge clk) begin
        write <= 1'b1;
        idata <= data;
    end

    @(posedge clk) write <= 1'b0;
end
endtask

task enqueu_clear_oe(
    input [7:0] data
);
begin
    @(posedge clk) begin
        write <= 1'b1;
        idata <= data;
        clear_flag <= 1'b1;
    end

    @(posedge clk) begin
        write <= 1'b0;
        clear_flag <= 1'b0;
    end
end
endtask


task dequeue(
    output  reg     [7:0]    data
);
begin
    @(posedge clk) begin
        read <= 1'b1;
        data <= odata;
    end

    @(posedge clk) read = 1'b0;
end
endtask

task en_dequeue(
    input           [7:0]   wdata,
    output  reg     [7:0]   rdata
);
begin
    @(posedge clk) begin
        read = 1'b1;
        write = 1'b1;
        idata = wdata;
    end

    @(posedge clk) begin
        rdata = odata;
        read = 1'b0;
        write = 1'b0;
    end
end
endtask

task clear_oe;
begin
    @(posedge clk) clear_flag <= 1'b1;
    @(posedge clk) clear_flag <= 1'b0;
end
endtask


task fifo_normal_test;
begin
    //Init
    regmode = 0;
    read = 0;
    write = 0;
    clk = 0;
    reset_n = 0;
    i = 0;
    scratch = 0;
    wdata = 0;
    rdata = 0;

    //ASSD Reset
    @(posedge clk) reset_n = 1'b1;

    `assert( elems, 5'h00 );
    `assert( full, 1'b0 );
    `assert( empty, 1'b1 );
    `assert( oeflag, 1'b0);

    //Fill fifo full
    repeat(16) begin
        enqueue(wdata);
        wdata = wdata + 1;
    end
    
    //Try force fill 
    enqueue( 8'hff );
    //Check Interrupt Flag
    @(posedge clk) `assert( oeflag, 1'b1);
    clear_oe();
    @(posedge clk) `assert( oeflag, 1'b0);
    //Clear & force fill
    enqueu_clear_oe( 8'hff );
    @(posedge clk) `assert( oeflag, 1'b1);

    clear_oe();
    @(posedge clk) begin
        `assert( elems, 5'h10 );
        `assert( full, 1'b1 );
        `assert( empty, 1'b0 );
        `assert( oeflag, 1'b0);
    end

    //Dequeue first element
    dequeue( scratch );
    `assert( scratch, rdata );
    rdata = rdata + 1;

    repeat(100) begin
        en_dequeue( wdata, scratch );
        `assert( scratch, rdata );
        rdata = rdata + 1;
        wdata = wdata + 1;
    end
end
endtask

//==VCD
initial
begin
    clk = 0;
    $dumpfile( "fifotest.vcd" );
    $dumpvars;
end

always #2 clk = ~clk;

initial
begin
    fifo_normal_test();
    #20 $finish;
end

//==DUT
uart1655_axil_fifo dut(
    .regmode(regmode),
    .idata(idata),
    .write(write),
    .odata(odata),
    .read(read),
    .elems(elems),
    .empty(empty),
    .full(full),
    .oeflag(oeflag),
    .clear_flag(clear_flag),
    .clk(clk),
    .reset_n(reset_n)
);

endmodule

test/fifotest.vcd
$date
	Thu Apr 18 17:03:57 2019
$end
$version
	Icarus Verilog
$end
$timescale
	10ps
$end
$scope module fifotest $end
$var wire 1 ! oeflag $end
$var wire 8 " odata [7:0] $end
$var wire 1 # full $end
$var wire 1 $ empty $end
$var wire 5 % elems [4:0] $end
$var reg 1 & clear_flag $end
$var reg 1 ' clk $end
$var reg 8 ( i [7:0] $end
$var reg 8 ) idata [7:0] $end
$var reg 8 * rdata [7:0] $end
$var reg 1 + read $end
$var reg 1 , regmode $end
$var reg 1 - reset_n $end
$var reg 8 . scratch [7:0] $end
$var reg 8 / wdata [7:0] $end
$var reg 1 0 write $end
$scope module dut $end
$var wire 1 & clear_flag $end
$var wire 1 ' clk $end
$var wire 5 1 elems [4:0] $end
$var wire 8 2 idata [7:0] $end
$var wire 8 3 odata [7:0] $end
$var wire 1 + read $end
$var wire 1 , regmode $end
$var wire 1 - reset_n $end
$var wire 1 4 valid_read $end
$var wire 1 5 valid_write $end
$var wire 1 0 write $end
$var wire 1 # full $end
$var wire 1 $ empty $end
$var reg 5 6 elems_r [4:0] $end
$var reg 1 ! oeflag $end
$var reg 1 7 reg_full $end
$var reg 4 8 rptr [3:0] $end
$var reg 4 9 wptr [3:0] $end
$upscope $end
$scope task clear_oe $end
$upscope $end
$scope task dequeue $end
$var reg 8 : data [7:0] $end
$upscope $end
$scope task en_dequeue $end
$var reg 8 ; rdata [7:0] $end
$var reg 8 < wdata [7:0] $end
$upscope $end
$scope task enqueu_clear_oe $end
$var reg 8 = data [7:0] $end
$upscope $end
$scope task enqueue $end
$var reg 8 > data [7:0] $end
$upscope $end
$scope task fifo_normal_test $end
$upscope $end
$upscope $end
$enddefinitions $end
#0
$dumpvars
bx >
bx =
bx <
bx ;
bx :
b0 9
b0 8
07
b0 6
05
04
bx 3
bx 2
b0 1
00
b0 /
b0 .
0-
0,
0+
b0 *
bx )
b0 (
0'
0&
b0 %
1$
0#
bx "
0!
$end
#200
b0 >
1-
1'
#400
0'
#600
15
b0 )
b0 2
10
1'
#800
0'
#1000
05
17
b1 9
0$
b1 %
b1 1
b1 6
00
b0 "
b0 3
b1 >
b1 /
1'
#1200
0'
#1400
15
b1 )
b1 2
10
1'
#1600
0'
#1800
05
b10 9
b10 %
b10 1
b10 6
00
b10 >
b10 /
1'
#2000
0'
#2200
15
b10 )
b10 2
10
1'
#2400
0'
#2600
05
b11 9
b11 %
b11 1
b11 6
00
b11 >
b11 /
1'
#2800
0'
#3000
15
b11 )
b11 2
10
1'
#3200
0'
#3400
05
b100 9
b100 %
b100 1
b100 6
00
b100 >
b100 /
1'
#3600
0'
#3800
15
b100 )
b100 2
10
1'
#4000
0'
#4200
05
b101 9
b101 %
b101 1
b101 6
00
b101 >
b101 /
1'
#4400
0'
#4600
15
b101 )
b101 2
10
1'
#4800
0'
#5000
05
b110 9
b110 %
b110 1
b110 6
00
b110 >
b110 /
1'
#5200
0'
#5400
15
b110 )
b110 2
10
1'
#5600
0'
#5800
05
b111 9
b111 %
b111 1
b111 6
00
b111 >
b111 /
1'
#6000
0'
#6200
15
b111 )
b111 2
10
1'
#6400
0'
#6600
05
b1000 9
b1000 %
b1000 1
b1000 6
00
b1000 >
b1000 /
1'
#6800
0'
#7000
15
b1000 )
b1000 2
10
1'
#7200
0'
#7400
05
b1001 9
b1001 %
b1001 1
b1001 6
00
b1001 >
b1001 /
1'
#7600
0'
#7800
15
b1001 )
b1001 2
10
1'
#8000
0'
#8200
05
b1010 9
b1010 %
b1010 1
b1010 6
00
b1010 >
b1010 /
1'
#8400
0'
#8600
15
b1010 )
b1010 2
10
1'
#8800
0'
#9000
05
b1011 9
b1011 %
b1011 1
b1011 6
00
b1011 >
b1011 /
1'
#9200
0'
#9400
15
b1011 )
b1011 2
10
1'
#9600
0'
#9800
05
b1100 9
b1100 %
b1100 1
b1100 6
00
b1100 >
b1100 /
1'
#10000
0'
#10200
15
b1100 )
b1100 2
10
1'
#10400
0'
#10600
05
b1101 9
b1101 %
b1101 1
b1101 6
00
b1101 >
b1101 /
1'
#10800
0'
#11000
15
b1101 )
b1101 2
10
1'
#11200
0'
#11400
05
b1110 9
b1110 %
b1110 1
b1110 6
00
b1110 >
b1110 /
1'
#11600
0'
#11800
15
b1110 )
b1110 2
10
1'
#12000
0'
#12200
05
b1111 9
b1111 %
b1111 1
b1111 6
00
b1111 >
b1111 /
1'
#12400
0'
#12600
15
b1111 )
b1111 2
10
1'
#12800
0'
#13000
05
b0 9
1#
b10000 %
b10000 1
b10000 6
00
b11111111 >
b10000 /
1'
#13200
0'
#13400
b11111111 )
b11111111 2
10
1'
#13600
0'
#13800
1!
00
1'
#14000
0'
#14200
1'
#14400
0'
#14600
1&
1'
#14800
0'
#15000
0!
0&
1'
#15200
0'
#15400
b11111111 =
1'
#15600
0'
#15800
1&
10
1'
#16000
0'
#16200
1!
0&
00
1'
#16400
0'
#16600
1'
#16800
0'
#17000
1&
1'
#17200
0'
#17400
0!
0&
1'
#17600
0'
#17800
1'
#18000
0'
#18200
14
b0 :
1+
1'
#18400
0'
#18600
b1 "
b1 3
b1 8
0#
b1111 %
b1111 1
b1111 6
04
b10000 <
b1 *
0+
1'
#18800
0'
#19000
15
14
b10000 )
b10000 2
10
1+
1'
#19200
0'
#19400
b10 "
b10 3
b10 8
b1 9
05
04
b10001 <
b10001 /
b10 *
b1 .
00
0+
b1 ;
1'
#19600
0'
#19800
15
14
b10001 )
b10001 2
10
1+
1'
#20000
0'
#20200
b11 "
b11 3
b11 8
b10 9
05
04
b10010 <
b10010 /
b11 *
b10 .
00
0+
b10 ;
1'
#20400
0'
#20600
15
14
b10010 )
b10010 2
10
1+
1'
#20800
0'
#21000
b100 "
b100 3
b100 8
b11 9
05
04
b10011 <
b10011 /
b100 *
b11 .
00
0+
b11 ;
1'
#21200
0'
#21400
15
14
b10011 )
b10011 2
10
1+
1'
#21600
0'
#21800
b101 "
b101 3
b101 8
b100 9
05
04
b10100 <
b10100 /
b101 *
b100 .
00
0+
b100 ;
1'
#22000
0'
#22200
15
14
b10100 )
b10100 2
10
1+
1'
#22400
0'
#22600
b110 "
b110 3
b110 8
b101 9
05
04
b10101 <
b10101 /
b110 *
b101 .
00
0+
b101 ;
1'
#22800
0'
#23000
15
14
b10101 )
b10101 2
10
1+
1'
#23200
0'
#23400
b111 "
b111 3
b111 8
b110 9
05
04
b10110 <
b10110 /
b111 *
b110 .
00
0+
b110 ;
1'
#23600
0'
#23800
15
14
b10110 )
b10110 2
10
1+
1'
#24000
0'
#24200
b1000 "
b1000 3
b1000 8
b111 9
05
04
b10111 <
b10111 /
b1000 *
b111 .
00
0+
b111 ;
1'
#24400
0'
#24600
15
14
b10111 )
b10111 2
10
1+
1'
#24800
0'
#25000
b1001 "
b1001 3
b1001 8
b1000 9
05
04
b11000 <
b11000 /
b1001 *
b1000 .
00
0+
b1000 ;
1'
#25200
0'
#25400
15
14
b11000 )
b11000 2
10
1+
1'
#25600
0'
#25800
b1010 "
b1010 3
b1010 8
b1001 9
05
04
b11001 <
b11001 /
b1010 *
b1001 .
00
0+
b1001 ;
1'
#26000
0'
#26200
15
14
b11001 )
b11001 2
10
1+
1'
#26400
0'
#26600
b1011 "
b1011 3
b1011 8
b1010 9
05
04
b11010 <
b11010 /
b1011 *
b1010 .
00
0+
b1010 ;
1'
#26800
0'
#27000
15
14
b11010 )
b11010 2
10
1+
1'
#27200
0'
#27400
b1100 "
b1100 3
b1100 8
b1011 9
05
04
b11011 <
b11011 /
b1100 *
b1011 .
00
0+
b1011 ;
1'
#27600
0'
#27800
15
14
b11011 )
b11011 2
10
1+
1'
#28000
0'
#28200
b1101 "
b1101 3
b1101 8
b1100 9
05
04
b11100 <
b11100 /
b1101 *
b1100 .
00
0+
b1100 ;
1'
#28400
0'
#28600
15
14
b11100 )
b11100 2
10
1+
1'
#28800
0'
#29000
b1110 "
b1110 3
b1110 8
b1101 9
05
04
b11101 <
b11101 /
b1110 *
b1101 .
00
0+
b1101 ;
1'
#29200
0'
#29400
15
14
b11101 )
b11101 2
10
1+
1'
#29600
0'
#29800
b1111 "
b1111 3
b1111 8
b1110 9
05
04
b11110 <
b11110 /
b1111 *
b1110 .
00
0+
b1110 ;
1'
#30000
0'
#30200
15
14
b11110 )
b11110 2
10
1+
1'
#30400
0'
#30600
b10000 "
b10000 3
b0 8
b1111 9
05
04
b11111 <
b11111 /
b10000 *
b1111 .
00
0+
b1111 ;
1'
#30800
0'
#31000
15
14
b11111 )
b11111 2
10
1+
1'
#31200
0'
#31400
b10001 "
b10001 3
b1 8
b0 9
05
04
b100000 <
b100000 /
b10001 *
b10000 .
00
0+
b10000 ;
1'
#31600
0'
#31800
15
14
b100000 )
b100000 2
10
1+
1'
#32000
0'
#32200
b10010 "
b10010 3
b10 8
b1 9
05
04
b100001 <
b100001 /
b10010 *
b10001 .
00
0+
b10001 ;
1'
#32400
0'
#32600
15
14
b100001 )
b100001 2
10
1+
1'
#32800
0'
#33000
b10011 "
b10011 3
b11 8
b10 9
05
04
b100010 <
b100010 /
b10011 *
b10010 .
00
0+
b10010 ;
1'
#33200
0'
#33400
15
14
b100010 )
b100010 2
10
1+
1'
#33600
0'
#33800
b10100 "
b10100 3
b100 8
b11 9
05
04
b100011 <
b100011 /
b10100 *
b10011 .
00
0+
b10011 ;
1'
#34000
0'
#34200
15
14
b100011 )
b100011 2
10
1+
1'
#34400
0'
#34600
b10101 "
b10101 3
b101 8
b100 9
05
04
b100100 <
b100100 /
b10101 *
b10100 .
00
0+
b10100 ;
1'
#34800
0'
#35000
15
14
b100100 )
b100100 2
10
1+
1'
#35200
0'
#35400
b10110 "
b10110 3
b110 8
b101 9
05
04
b100101 <
b100101 /
b10110 *
b10101 .
00
0+
b10101 ;
1'
#35600
0'
#35800
15
14
b100101 )
b100101 2
10
1+
1'
#36000
0'
#36200
b10111 "
b10111 3
b111 8
b110 9
05
04
b100110 <
b100110 /
b10111 *
b10110 .
00
0+
b10110 ;
1'
#36400
0'
#36600
15
14
b100110 )
b100110 2
10
1+
1'
#36800
0'
#37000
b11000 "
b11000 3
b1000 8
b111 9
05
04
b100111 <
b100111 /
b11000 *
b10111 .
00
0+
b10111 ;
1'
#37200
0'
#37400
15
14
b100111 )
b100111 2
10
1+
1'
#37600
0'
#37800
b11001 "
b11001 3
b1001 8
b1000 9
05
04
b101000 <
b101000 /
b11001 *
b11000 .
00
0+
b11000 ;
1'
#38000
0'
#38200
15
14
b101000 )
b101000 2
10
1+
1'
#38400
0'
#38600
b11010 "
b11010 3
b1010 8
b1001 9
05
04
b101001 <
b101001 /
b11010 *
b11001 .
00
0+
b11001 ;
1'
#38800
0'
#39000
15
14
b101001 )
b101001 2
10
1+
1'
#39200
0'
#39400
b11011 "
b11011 3
b1011 8
b1010 9
05
04
b101010 <
b101010 /
b11011 *
b11010 .
00
0+
b11010 ;
1'
#39600
0'
#39800
15
14
b101010 )
b101010 2
10
1+
1'
#40000
0'
#40200
b11100 "
b11100 3
b1100 8
b1011 9
05
04
b101011 <
b101011 /
b11100 *
b11011 .
00
0+
b11011 ;
1'
#40400
0'
#40600
15
14
b101011 )
b101011 2
10
1+
1'
#40800
0'
#41000
b11101 "
b11101 3
b1101 8
b1100 9
05
04
b101100 <
b101100 /
b11101 *
b11100 .
00
0+
b11100 ;
1'
#41200
0'
#41400
15
14
b101100 )
b101100 2
10
1+
1'
#41600
0'
#41800
b11110 "
b11110 3
b1110 8
b1101 9
05
04
b101101 <
b101101 /
b11110 *
b11101 .
00
0+
b11101 ;
1'
#42000
0'
#42200
15
14
b101101 )
b101101 2
10
1+
1'
#42400
0'
#42600
b11111 "
b11111 3
b1111 8
b1110 9
05
04
b101110 <
b101110 /
b11111 *
b11110 .
00
0+
b11110 ;
1'
#42800
0'
#43000
15
14
b101110 )
b101110 2
10
1+
1'
#43200
0'
#43400
b100000 "
b100000 3
b0 8
b1111 9
05
04
b101111 <
b101111 /
b100000 *
b11111 .
00
0+
b11111 ;
1'
#43600
0'
#43800
15
14
b101111 )
b101111 2
10
1+
1'
#44000
0'
#44200
b100001 "
b100001 3
b1 8
b0 9
05
04
b110000 <
b110000 /
b100001 *
b100000 .
00
0+
b100000 ;
1'
#44400
0'
#44600
15
14
b110000 )
b110000 2
10
1+
1'
#44800
0'
#45000
b100010 "
b100010 3
b10 8
b1 9
05
04
b110001 <
b110001 /
b100010 *
b100001 .
00
0+
b100001 ;
1'
#45200
0'
#45400
15
14
b110001 )
b110001 2
10
1+
1'
#45600
0'
#45800
b100011 "
b100011 3
b11 8
b10 9
05
04
b110010 <
b110010 /
b100011 *
b100010 .
00
0+
b100010 ;
1'
#46000
0'
#46200
15
14
b110010 )
b110010 2
10
1+
1'
#46400
0'
#46600
b100100 "
b100100 3
b100 8
b11 9
05
04
b110011 <
b110011 /
b100100 *
b100011 .
00
0+
b100011 ;
1'
#46800
0'
#47000
15
14
b110011 )
b110011 2
10
1+
1'
#47200
0'
#47400
b100101 "
b100101 3
b101 8
b100 9
05
04
b110100 <
b110100 /
b100101 *
b100100 .
00
0+
b100100 ;
1'
#47600
0'
#47800
15
14
b110100 )
b110100 2
10
1+
1'
#48000
0'
#48200
b100110 "
b100110 3
b110 8
b101 9
05
04
b110101 <
b110101 /
b100110 *
b100101 .
00
0+
b100101 ;
1'
#48400
0'
#48600
15
14
b110101 )
b110101 2
10
1+
1'
#48800
0'
#49000
b100111 "
b100111 3
b111 8
b110 9
05
04
b110110 <
b110110 /
b100111 *
b100110 .
00
0+
b100110 ;
1'
#49200
0'
#49400
15
14
b110110 )
b110110 2
10
1+
1'
#49600
0'
#49800
b101000 "
b101000 3
b1000 8
b111 9
05
04
b110111 <
b110111 /
b101000 *
b100111 .
00
0+
b100111 ;
1'
#50000
0'
#50200
15
14
b110111 )
b110111 2
10
1+
1'
#50400
0'
#50600
b101001 "
b101001 3
b1001 8
b1000 9
05
04
b111000 <
b111000 /
b101001 *
b101000 .
00
0+
b101000 ;
1'
#50800
0'
#51000
15
14
b111000 )
b111000 2
10
1+
1'
#51200
0'
#51400
b101010 "
b101010 3
b1010 8
b1001 9
05
04
b111001 <
b111001 /
b101010 *
b101001 .
00
0+
b101001 ;
1'
#51600
0'
#51800
15
14
b111001 )
b111001 2
10
1+
1'
#52000
0'
#52200
b101011 "
b101011 3
b1011 8
b1010 9
05
04
b111010 <
b111010 /
b101011 *
b101010 .
00
0+
b101010 ;
1'
#52400
0'
#52600
15
14
b111010 )
b111010 2
10
1+
1'
#52800
0'
#53000
b101100 "
b101100 3
b1100 8
b1011 9
05
04
b111011 <
b111011 /
b101100 *
b101011 .
00
0+
b101011 ;
1'
#53200
0'
#53400
15
14
b111011 )
b111011 2
10
1+
1'
#53600
0'
#53800
b101101 "
b101101 3
b1101 8
b1100 9
05
04
b111100 <
b111100 /
b101101 *
b101100 .
00
0+
b101100 ;
1'
#54000
0'
#54200
15
14
b111100 )
b111100 2
10
1+
1'
#54400
0'
#54600
b101110 "
b101110 3
b1110 8
b1101 9
05
04
b111101 <
b111101 /
b101110 *
b101101 .
00
0+
b101101 ;
1'
#54800
0'
#55000
15
14
b111101 )
b111101 2
10
1+
1'
#55200
0'
#55400
b101111 "
b101111 3
b1111 8
b1110 9
05
04
b111110 <
b111110 /
b101111 *
b101110 .
00
0+
b101110 ;
1'
#55600
0'
#55800
15
14
b111110 )
b111110 2
10
1+
1'
#56000
0'
#56200
b110000 "
b110000 3
b0 8
b1111 9
05
04
b111111 <
b111111 /
b110000 *
b101111 .
00
0+
b101111 ;
1'
#56400
0'
#56600
15
14
b111111 )
b111111 2
10
1+
1'
#56800
0'
#57000
b110001 "
b110001 3
b1 8
b0 9
05
04
b1000000 <
b1000000 /
b110001 *
b110000 .
00
0+
b110000 ;
1'
#57200
0'
#57400
15
14
b1000000 )
b1000000 2
10
1+
1'
#57600
0'
#57800
b110010 "
b110010 3
b10 8
b1 9
05
04
b1000001 <
b1000001 /
b110010 *
b110001 .
00
0+
b110001 ;
1'
#58000
0'
#58200
15
14
b1000001 )
b1000001 2
10
1+
1'
#58400
0'
#58600
b110011 "
b110011 3
b11 8
b10 9
05
04
b1000010 <
b1000010 /
b110011 *
b110010 .
00
0+
b110010 ;
1'
#58800
0'
#59000
15
14
b1000010 )
b1000010 2
10
1+
1'
#59200
0'
#59400
b110100 "
b110100 3
b100 8
b11 9
05
04
b1000011 <
b1000011 /
b110100 *
b110011 .
00
0+
b110011 ;
1'
#59600
0'
#59800
15
14
b1000011 )
b1000011 2
10
1+
1'
#60000
0'
#60200
b110101 "
b110101 3
b101 8
b100 9
05
04
b1000100 <
b1000100 /
b110101 *
b110100 .
00
0+
b110100 ;
1'
#60400
0'
#60600
15
14
b1000100 )
b1000100 2
10
1+
1'
#60800
0'
#61000
b110110 "
b110110 3
b110 8
b101 9
05
04
b1000101 <
b1000101 /
b110110 *
b110101 .
00
0+
b110101 ;
1'
#61200
0'
#61400
15
14
b1000101 )
b1000101 2
10
1+
1'
#61600
0'
#61800
b110111 "
b110111 3
b111 8
b110 9
05
04
b1000110 <
b1000110 /
b110111 *
b110110 .
00
0+
b110110 ;
1'
#62000
0'
#62200
15
14
b1000110 )
b1000110 2
10
1+
1'
#62400
0'
#62600
b111000 "
b111000 3
b1000 8
b111 9
05
04
b1000111 <
b1000111 /
b111000 *
b110111 .
00
0+
b110111 ;
1'
#62800
0'
#63000
15
14
b1000111 )
b1000111 2
10
1+
1'
#63200
0'
#63400
b111001 "
b111001 3
b1001 8
b1000 9
05
04
b1001000 <
b1001000 /
b111001 *
b111000 .
00
0+
b111000 ;
1'
#63600
0'
#63800
15
14
b1001000 )
b1001000 2
10
1+
1'
#64000
0'
#64200
b111010 "
b111010 3
b1010 8
b1001 9
05
04
b1001001 <
b1001001 /
b111010 *
b111001 .
00
0+
b111001 ;
1'
#64400
0'
#64600
15
14
b1001001 )
b1001001 2
10
1+
1'
#64800
0'
#65000
b111011 "
b111011 3
b1011 8
b1010 9
05
04
b1001010 <
b1001010 /
b111011 *
b111010 .
00
0+
b111010 ;
1'
#65200
0'
#65400
15
14
b1001010 )
b1001010 2
10
1+
1'
#65600
0'
#65800
b111100 "
b111100 3
b1100 8
b1011 9
05
04
b1001011 <
b1001011 /
b111100 *
b111011 .
00
0+
b111011 ;
1'
#66000
0'
#66200
15
14
b1001011 )
b1001011 2
10
1+
1'
#66400
0'
#66600
b111101 "
b111101 3
b1101 8
b1100 9
05
04
b1001100 <
b1001100 /
b111101 *
b111100 .
00
0+
b111100 ;
1'
#66800
0'
#67000
15
14
b1001100 )
b1001100 2
10
1+
1'
#67200
0'
#67400
b111110 "
b111110 3
b1110 8
b1101 9
05
04
b1001101 <
b1001101 /
b111110 *
b111101 .
00
0+
b111101 ;
1'
#67600
0'
#67800
15
14
b1001101 )
b1001101 2
10
1+
1'
#68000
0'
#68200
b111111 "
b111111 3
b1111 8
b1110 9
05
04
b1001110 <
b1001110 /
b111111 *
b111110 .
00
0+
b111110 ;
1'
#68400
0'
#68600
15
14
b1001110 )
b1001110 2
10
1+
1'
#68800
0'
#69000
b1000000 "
b1000000 3
b0 8
b1111 9
05
04
b1001111 <
b1001111 /
b1000000 *
b111111 .
00
0+
b111111 ;
1'
#69200
0'
#69400
15
14
b1001111 )
b1001111 2
10
1+
1'
#69600
0'
#69800
b1000001 "
b1000001 3
b1 8
b0 9
05
04
b1010000 <
b1010000 /
b1000001 *
b1000000 .
00
0+
b1000000 ;
1'
#70000
0'
#70200
15
14
b1010000 )
b1010000 2
10
1+
1'
#70400
0'
#70600
b1000010 "
b1000010 3
b10 8
b1 9
05
04
b1010001 <
b1010001 /
b1000010 *
b1000001 .
00
0+
b1000001 ;
1'
#70800
0'
#71000
15
14
b1010001 )
b1010001 2
10
1+
1'
#71200
0'
#71400
b1000011 "
b1000011 3
b11 8
b10 9
05
04
b1010010 <
b1010010 /
b1000011 *
b1000010 .
00
0+
b1000010 ;
1'
#71600
0'
#71800
15
14
b1010010 )
b1010010 2
10
1+
1'
#72000
0'
#72200
b1000100 "
b1000100 3
b100 8
b11 9
05
04
b1010011 <
b1010011 /
b1000100 *
b1000011 .
00
0+
b1000011 ;
1'
#72400
0'
#72600
15
14
b1010011 )
b1010011 2
10
1+
1'
#72800
0'
#73000
b1000101 "
b1000101 3
b101 8
b100 9
05
04
b1010100 <
b1010100 /
b1000101 *
b1000100 .
00
0+
b1000100 ;
1'
#73200
0'
#73400
15
14
b1010100 )
b1010100 2
10
1+
1'
#73600
0'
#73800
b1000110 "
b1000110 3
b110 8
b101 9
05
04
b1010101 <
b1010101 /
b1000110 *
b1000101 .
00
0+
b1000101 ;
1'
#74000
0'
#74200
15
14
b1010101 )
b1010101 2
10
1+
1'
#74400
0'
#74600
b1000111 "
b1000111 3
b111 8
b110 9
05
04
b1010110 <
b1010110 /
b1000111 *
b1000110 .
00
0+
b1000110 ;
1'
#74800
0'
#75000
15
14
b1010110 )
b1010110 2
10
1+
1'
#75200
0'
#75400
b1001000 "
b1001000 3
b1000 8
b111 9
05
04
b1010111 <
b1010111 /
b1001000 *
b1000111 .
00
0+
b1000111 ;
1'
#75600
0'
#75800
15
14
b1010111 )
b1010111 2
10
1+
1'
#76000
0'
#76200
b1001001 "
b1001001 3
b1001 8
b1000 9
05
04
b1011000 <
b1011000 /
b1001001 *
b1001000 .
00
0+
b1001000 ;
1'
#76400
0'
#76600
15
14
b1011000 )
b1011000 2
10
1+
1'
#76800
0'
#77000
b1001010 "
b1001010 3
b1010 8
b1001 9
05
04
b1011001 <
b1011001 /
b1001010 *
b1001001 .
00
0+
b1001001 ;
1'
#77200
0'
#77400
15
14
b1011001 )
b1011001 2
10
1+
1'
#77600
0'
#77800
b1001011 "
b1001011 3
b1011 8
b1010 9
05
04
b1011010 <
b1011010 /
b1001011 *
b1001010 .
00
0+
b1001010 ;
1'
#78000
0'
#78200
15
14
b1011010 )
b1011010 2
10
1+
1'
#78400
0'
#78600
b1001100 "
b1001100 3
b1100 8
b1011 9
05
04
b1011011 <
b1011011 /
b1001100 *
b1001011 .
00
0+
b1001011 ;
1'
#78800
0'
#79000
15
14
b1011011 )
b1011011 2
10
1+
1'
#79200
0'
#79400
b1001101 "
b1001101 3
b1101 8
b1100 9
05
04
b1011100 <
b1011100 /
b1001101 *
b1001100 .
00
0+
b1001100 ;
1'
#79600
0'
#79800
15
14
b1011100 )
b1011100 2
10
1+
1'
#80000
0'
#80200
b1001110 "
b1001110 3
b1110 8
b1101 9
05
04
b1011101 <
b1011101 /
b1001110 *
b1001101 .
00
0+
b1001101 ;
1'
#80400
0'
#80600
15
14
b1011101 )
b1011101 2
10
1+
1'
#80800
0'
#81000
b1001111 "
b1001111 3
b1111 8
b1110 9
05
04
b1011110 <
b1011110 /
b1001111 *
b1001110 .
00
0+
b1001110 ;
1'
#81200
0'
#81400
15
14
b1011110 )
b1011110 2
10
1+
1'
#81600
0'
#81800
b1010000 "
b1010000 3
b0 8
b1111 9
05
04
b1011111 <
b1011111 /
b1010000 *
b1001111 .
00
0+
b1001111 ;
1'
#82000
0'
#82200
15
14
b1011111 )
b1011111 2
10
1+
1'
#82400
0'
